bit7display/display7.v
module segment7(
     bcd,
     seg
    );
     
     //Declare inputs,outputs and internal variables.
     input [3:0] bcd;
     output [6:0] seg;
     reg [6:0] seg;

//always block for converting bcd digit into 7 segment format
    always @(bcd)
    begin
        case (bcd) //case statement
            4'b0000 : seg = 7'b0000001;
            4'b0001 : seg = 7'b1001111;
            4'b0010 : seg = 7'b0010010;
            4'b0011 : seg = 7'b0000110;
            4'b0100 : seg = 7'b1001100;
            4'b0101 : seg = 7'b0100100;
            4'b0110 : seg = 7'b0100000;
            4'b0111 : seg = 7'b0001111;
            4'b1000 : seg = 7'b0000000;
            4'b1001 : seg = 7'b0000100;
            //switch off 7 segment character when the bcd digit is not a decimal number.
            default : seg = 7'b1111111; 
        endcase
    end
    
endmodule

bit7display/display7_tb.v
module tb_segment7;

    reg [3:0] bcd;
    wire [6:0] seg;
    integer i;

    // Instantiate the Unit Under Test (UUT)
    segment7 uut (
        .bcd(bcd), 
        .seg(seg)
    );

//Apply inputs
    initial begin
         $dumpfile ("displaytest.vcd");
         $dumpvars (0, tb_segment7);
         $monitor ($time, " bcd=%4b and seg=%7b", bcd,seg);
         begin
        bcd=4'b0000; #100;
        bcd=4'b0001; #100;
        bcd=4'b0010; #100;
        bcd=4'b0011; #100;
        bcd=4'b0100; #100;
        bcd=4'b0101; #100;
        bcd=4'b0110; #100;
        bcd=4'b0111; #100;
        bcd=4'b1000; #100;
        bcd=4'b1001; #100;
        bcd=4'b1010; #100;
        bcd=4'b1011; #100;
        bcd=4'b1100; #100;
        bcd=4'b1101; #100;
        bcd=4'b1110; #100;
        bcd=4'b1111; #100;
         end
        $finish;  
    end
      
endmodule

bit7display/displaytest.vcd
$date
	Thu Jan 05 01:58:41 2023
$end
$version
	Icarus Verilog
$end
$timescale
	1s
$end
$scope module tb_segment7 $end
$var wire 7 ! seg [6:0] $end
$var reg 4 " bcd [3:0] $end
$scope module uut $end
$var wire 4 # bcd [3:0] $end
$var reg 7 $ seg [6:0] $end
$upscope $end
$upscope $end
$enddefinitions $end
$comment Show the parameter values. $end
$dumpall
$end
#0
$dumpvars
b1 $
b0 #
b0 "
b1 !
$end
#100
b1001111 !
b1001111 $
b1 "
b1 #
#200
b10010 !
b10010 $
b10 "
b10 #
#300
b110 !
b110 $
b11 "
b11 #
#400
b1001100 !
b1001100 $
b100 "
b100 #
#500
b100100 !
b100100 $
b101 "
b101 #
#600
b100000 !
b100000 $
b110 "
b110 #
#700
b1111 !
b1111 $
b111 "
b111 #
#800
b0 !
b0 $
b1000 "
b1000 #
#900
b100 !
b100 $
b1001 "
b1001 #
#1000
b1111111 !
b1111111 $
b1010 "
b1010 #
#1100
b1011 "
b1011 #
#1200
b1100 "
b1100 #
#1300
b1101 "
b1101 #
#1400
b1110 "
b1110 #
#1500
b1111 "
b1111 #
