bit7display/display7.v
module segment7(
     bcd,
     seg
    );
     
     //Declare inputs,outputs and internal variables.
     input [3:0] bcd;
     output [6:0] seg;
     reg [6:0] seg;

//always block for converting bcd digit into 7 segment format
    always @(bcd)
    begin
        case (bcd) //case statement
            4'b0000 : seg = 7'b0000001; //0
            4'b0001 : seg = 7'b1001111; //1
            4'b0010 : seg = 7'b0010010; //2
            4'b0011 : seg = 7'b0000110; //3
            4'b0100 : seg = 7'b1001100; //4
            4'b0101 : seg = 7'b0100100; //5
            4'b0110 : seg = 7'b0100000; //6
            4'b0111 : seg = 7'b0001111; //7
            4'b1000 : seg = 7'b0000000; //8
            4'b1001 : seg = 7'b0000100; //9
            4'b1010 : seg = 7'b1100000; //A
            4'b1011 : seg = 7'b0000000; //B
            4'b1100 : seg = 7'b0110001; //C
            4'b1101 : seg = 7'b1000010; //D
            4'b1110 : seg = 7'b0110000; //E
            4'b1111 : seg = 7'b0111000; //F
            default : seg = 7'b1111111; 
        endcase
    end
    
endmodule

bit7display/display7_tb.v
module tb_segment7;

    reg [3:0] bcd;
    wire [6:0] seg;
    integer i;

    // Instantiate the Unit Under Test (UUT)
    segment7 uut (
        .bcd(bcd), 
        .seg(seg)
    );

//Apply inputs
    initial begin
         $dumpfile ("displaytest.vcd");
         $dumpvars (0, tb_segment7);
         $monitor ($time, " bcd=%4b and seg=%7b", bcd,seg);
         begin
        bcd=4'b0000; #1;
        bcd=4'b0001; #1;
        bcd=4'b0010; #1;
        bcd=4'b0011; #1;
        bcd=4'b0100; #1;
        bcd=4'b0101; #1;
        bcd=4'b0110; #1;
        bcd=4'b0111; #1;
        bcd=4'b1000; #1;
        bcd=4'b1001; #1;
        bcd=4'b1010; #1;
        bcd=4'b1011; #1;
        bcd=4'b1100; #1;
        bcd=4'b1101; #1;
        bcd=4'b1110; #1;
        bcd=4'b1111; #1;
         end
        $finish;  
    end
      
endmodule

bit7display/displaytest.vcd
$date
	Thu Jan 05 12:05:36 2023
$end
$version
	Icarus Verilog
$end
$timescale
	1s
$end
$scope module tb_segment7 $end
$var wire 7 ! seg [6:0] $end
$var reg 4 " bcd [3:0] $end
$scope module uut $end
$var wire 4 # bcd [3:0] $end
$var reg 7 $ seg [6:0] $end
$upscope $end
$upscope $end
$enddefinitions $end
$comment Show the parameter values. $end
$dumpall
$end
#0
$dumpvars
b1 $
b0 #
b0 "
b1 !
$end
#1
b1001111 !
b1001111 $
b1 "
b1 #
#2
b10010 !
b10010 $
b10 "
b10 #
#3
b110 !
b110 $
b11 "
b11 #
#4
b1001100 !
b1001100 $
b100 "
b100 #
#5
b100100 !
b100100 $
b101 "
b101 #
#6
b100000 !
b100000 $
b110 "
b110 #
#7
b1111 !
b1111 $
b111 "
b111 #
#8
b0 !
b0 $
b1000 "
b1000 #
#9
b100 !
b100 $
b1001 "
b1001 #
#10
b1100000 !
b1100000 $
b1010 "
b1010 #
#11
b0 !
b0 $
b1011 "
b1011 #
#12
b110001 !
b110001 $
b1100 "
b1100 #
#13
b1000010 !
b1000010 $
b1101 "
b1101 #
#14
b110000 !
b110000 $
b1110 "
b1110 #
#15
b111000 !
b111000 $
b1111 "
b1111 #
