RING COUNTER/ringcounter.v
module four_bit_ring_counter (
     input clock,
     input reset,
     output [3:0] q   );
 reg[3:0] a;
   always @(posedge clock)
     if (reset)
       a = 4'b0001;
     else
       begin
       a <=  a>>1; // Notice the blocking assignment
       a[3]<=a[0];
       end
   assign q = a;
 endmodule

RING COUNTER/ringcounter_tb.v
module stimulus;
   // Inputs
   reg clock;
   reg reset;
   // Outputs
 wire[3:0] q;
   // Instantiate the Unit Under Test (UUT)
   four_bit_ring_counter r1 (
     .clock(clock),
     .reset(reset),
     .q(q)
   );
 always #10 clock = ~clock;
   initial begin
       // Initialize Inputs
   clock = 0; 
   reset = 0;
   #5 reset = 1;
   #20 reset = 0;
   #500 $finish;
   end 
       initial begin
            $dumpfile("./ring.vcd");
            $dumpvars(0, stimulus);
            $monitor($time, " clock=%1b,reset=%1b,q=%4b",clock,reset,q);
       end
endmodule

RING COUNTER/ring.vcd
$date
	Fri Dec 09 16:55:42 2022
$end
$version
	Icarus Verilog
$end
$timescale
	1s
$end
$scope module stimulus $end
$var wire 4 ! q [3:0] $end
$var reg 1 " clock $end
$var reg 1 # reset $end
$scope module r1 $end
$var wire 1 " clock $end
$var wire 4 $ q [3:0] $end
$var wire 1 # reset $end
$var reg 4 % a [3:0] $end
$upscope $end
$upscope $end
$enddefinitions $end
$comment Show the parameter values. $end
$dumpall
$end
#0
$dumpvars
bx %
bx $
0#
0"
bx !
$end
#5
1#
#10
b1 !
b1 $
b1 %
1"
#20
0"
#25
0#
#30
b1000 !
b1000 $
b1000 %
1"
#40
0"
#50
b100 !
b100 $
b100 %
1"
#60
0"
#70
b10 !
b10 $
b10 %
1"
#80
0"
#90
b1 !
b1 $
b1 %
1"
#100
0"
#110
b1000 !
b1000 $
b1000 %
1"
#120
0"
#130
b100 !
b100 $
b100 %
1"
#140
0"
#150
b10 !
b10 $
b10 %
1"
#160
0"
#170
b1 !
b1 $
b1 %
1"
#180
0"
#190
b1000 !
b1000 $
b1000 %
1"
#200
0"
#210
b100 !
b100 $
b100 %
1"
#220
0"
#230
b10 !
b10 $
b10 %
1"
#240
0"
#250
b1 !
b1 $
b1 %
1"
#260
0"
#270
b1000 !
b1000 $
b1000 %
1"
#280
0"
#290
b100 !
b100 $
b100 %
1"
#300
0"
#310
b10 !
b10 $
b10 %
1"
#320
0"
#330
b1 !
b1 $
b1 %
1"
#340
0"
#350
b1000 !
b1000 $
b1000 %
1"
#360
0"
#370
b100 !
b100 $
b100 %
1"
#380
0"
#390
b10 !
b10 $
b10 %
1"
#400
0"
#410
b1 !
b1 $
b1 %
1"
#420
0"
#430
b1000 !
b1000 $
b1000 %
1"
#440
0"
#450
b100 !
b100 $
b100 %
1"
#460
0"
#470
b10 !
b10 $
b10 %
1"
#480
0"
#490
b1 !
b1 $
b1 %
1"
#500
0"
#510
b1000 !
b1000 $
b1000 %
1"
